{"assets/images/.DS_Store":["assets/images/.DS_Store"],"assets/images/img1.jpeg":["assets/images/img1.jpeg"],"assets/images/img2.jpeg":["assets/images/img2.jpeg"],"assets/images/img3.jpeg":["assets/images/img3.jpeg"],"assets/images/img4.jpg":["assets/images/img4.jpg"],"assets/images/img5.jpeg":["assets/images/img5.jpeg"],"assets/images/img6.jpeg":["assets/images/img6.jpeg"],"assets/images/img7.jpeg":["assets/images/img7.jpeg"],"assets/images/img8.jpg":["assets/images/img8.jpg"],"packages/cupertino_icons/assets/CupertinoIcons.ttf":["packages/cupertino_icons/assets/CupertinoIcons.ttf"]}